pydustry/__init__.py
pydustry/pydustry.py
pydustry_py-2.1.0.dist-info/LICENSE
pydustry_py-2.1.0.dist-info/METADATA
pydustry_py-2.1.0.dist-info/WHEEL
pydustry_py-2.1.0.dist-info/RECORD
