Metadata-Version: 2.1
Name: pydustry.py
Version: 2.1.0
Summary: Module for server information in the game Mindustry.
Home-page: https://github.com/RCR-OOP/pydustry.py
License: MIT
Keywords: midnustry,game,server,parser,infomation
Author: Romanin
Author-email: semina054@gmail.com
Requires-Python: >=3.6
Classifier: Development Status :: 5 - Production/Stable
Classifier: License :: OSI Approved :: MIT License
Classifier: Operating System :: OS Independent
Classifier: Programming Language :: Python :: 3
Classifier: Programming Language :: Python :: 3.6
Classifier: Programming Language :: Python :: 3.7
Classifier: Programming Language :: Python :: 3.8
Classifier: Programming Language :: Python :: 3.9
Classifier: Programming Language :: Python :: 3.10
Classifier: Programming Language :: Python :: 3.11
Classifier: Programming Language :: Python :: 3.12
Project-URL: Repository, https://github.com/RCR-OOP/pydustry.py
